{"repo": {"name": {"en-US": "forrestguice/SuntimesWidget-nightly"}, "description": {"en-US": "Nightly builds from forrestguice@runnervmjduv7"}, "icon": {"en-US": {"name": "/icons/icon.png", "sha256": "14664eed385cf3a0d5dc8a3b664b62288833cc9daffc17681203b32a2d9a55fc", "size": 1116}}, "address": "https://raw.githubusercontent.com/forrestguice/SuntimesWidget-nightly/master/fdroid/repo", "mirrors": [{"isPrimary": true, "url": "https://raw.githubusercontent.com/forrestguice/SuntimesWidget-nightly/master/fdroid/repo"}], "timestamp": 1771387827000, "categories": {"nightly": {"name": {"en-US": "nightly"}}}}, "packages": {"com.forrestguice.suntimeswidget.nightly": {"metadata": {"added": 1771387823000, "categories": ["nightly"], "issueTracker": "https://github.com/forrestguice/SuntimesWidget/issues", "lastUpdated": 1771387823000, "sourceCode": "https://github.com/forrestguice/SuntimesWidget", "authorName": "SuntimesWidget-nightly", "authorWebSite": "https://github.com/forrestguice", "name": {"en-US": "Suntimes (Debug)"}, "summary": {"en-US": "Nightly build of forrestguice/SuntimesWidget"}, "description": {"en-US": "Nightly build of forrestguice/SuntimesWidget"}, "icon": {"en-US": {"name": "/icons/com.forrestguice.suntimeswidget.nightly.2026021804.png", "sha256": "13bdffa832ca75666707a720f7496980ee8f6ffac2a99acc058a279bd5a6ebec", "size": 1044}}, "preferredSigner": "f8b6c4eac902352c55b6daed195b05e22bce012c1a32d15190f6fffb26b61206"}, "versions": {"15ca6d153fafd2ab04624384c197cd8b2c01bbda83748bec638808c28920d3b3": {"added": 1771387823000, "file": {"name": "/com.forrestguice.suntimeswidget.nightly_2026021804.apk", "sha256": "15ca6d153fafd2ab04624384c197cd8b2c01bbda83748bec638808c28920d3b3", "size": 11739170}, "manifest": {"versionName": "0.16.13-nightly", "versionCode": 2026021804, "usesSdk": {"minSdkVersion": 14, "targetSdkVersion": 30}, "signer": {"sha256": ["f8b6c4eac902352c55b6daed195b05e22bce012c1a32d15190f6fffb26b61206"]}, "usesPermission": [{"name": "android.permission.ACCESS_COARSE_LOCATION"}, {"name": "android.permission.ACCESS_FINE_LOCATION"}, {"name": "android.permission.ACCESS_LOCATION_EXTRA_COMMANDS"}, {"name": "com.android.alarm.permission.SET_ALARM"}, {"name": "android.permission.WRITE_EXTERNAL_STORAGE", "maxSdkVersion": 18}, {"name": "android.permission.READ_EXTERNAL_STORAGE", "maxSdkVersion": 18}, {"name": "android.permission.VIBRATE"}, {"name": "android.permission.RECEIVE_BOOT_COMPLETED"}, {"name": "android.permission.FOREGROUND_SERVICE"}, {"name": "android.permission.USE_FULL_SCREEN_INTENT"}, {"name": "android.permission.SCHEDULE_EXACT_ALARM"}, {"name": "android.permission.POST_NOTIFICATIONS"}, {"name": "org.codeaurora.permission.POWER_OFF_ALARM"}, {"name": "android.permission.REQUEST_IGNORE_BATTERY_OPTIMIZATIONS"}, {"name": "android.permission.ACCESS_NOTIFICATION_POLICY"}, {"name": "android.permission.QUERY_ALL_PACKAGES"}, {"name": "suntimes.nightly.permission.READ_CALCULATOR"}]}}}}}}